{
  "timestamp": "2025-09-20T17:48:59.693849",
  "version": "3.1",
  "progress": {
    "percentage": 87,
    "current_task": "devflow-startup-fix",
    "token_count": 0
  },
  "system": {
    "status": "PRODUCTION",
    "services_active": 7,
    "services_total": 8
  },
  "mode": "DEV",
  "last_tool": "unknown",
  "services": [
    {
      "name": "Database",
      "status": "active"
    },
    {
      "name": "Registry",
      "status": "active"
    },
    {
      "name": "Vector",
      "status": "active"
    },
    {
      "name": "Optimizer",
      "status": "active"
    },
    {
      "name": "CCR",
      "status": "active"
    },
    {
      "name": "Enforcement",
      "status": "active"
    },
    {
      "name": "Orchestrator",
      "status": "active"
    },
    {
      "name": "Synthetic",
      "status": "inactive"
    }
  ]
}