[
  {
    "timestamp": "2025-09-27T12:57:35.594758",
    "cpu_percent": 14.0380859375,
    "memory_percent": 0.18329620361328125,
    "disk_usage": 0.0,
    "tool_name": "Write",
    "execution_time": 1758970655.59479
  },
  {
    "timestamp": "2025-09-27T12:57:42.552649",
    "cpu_percent": 16.63818359375,
    "memory_percent": 0.18024444580078125,
    "disk_usage": 0.0,
    "tool_name": "TodoWrite",
    "execution_time": 1758970662.552672
  },
  {
    "timestamp": "2025-09-27T13:01:04.299730",
    "cpu_percent": 29.736328125,
    "memory_percent": 0.17948150634765625,
    "disk_usage": 0.0,
    "tool_name": "TodoWrite",
    "execution_time": 1758970864.299776
  },
  {
    "timestamp": "2025-09-27T13:01:26.858563",
    "cpu_percent": 28.082275390625,
    "memory_percent": 0.177764892578125,
    "disk_usage": 0.0,
    "tool_name": "Write",
    "execution_time": 1758970886.858591
  },
  {
    "timestamp": "2025-09-27T13:01:36.477872",
    "cpu_percent": 30.364990234375,
    "memory_percent": 0.1811981201171875,
    "disk_usage": 0.0,
    "tool_name": "Read",
    "execution_time": 1758970896.477907
  },
  {
    "timestamp": "2025-09-27T13:01:42.018277",
    "cpu_percent": 29.931640625,
    "memory_percent": 0.18138885498046875,
    "disk_usage": 0.0,
    "tool_name": "Edit",
    "execution_time": 1758970902.018304
  },
  {
    "timestamp": "2025-09-27T13:01:51.146321",
    "cpu_percent": 28.2470703125,
    "memory_percent": 0.1861572265625,
    "disk_usage": 0.0,
    "tool_name": "TodoWrite",
    "execution_time": 1758970911.146345
  },
  {
    "timestamp": "2025-09-27T13:02:26.735084",
    "cpu_percent": 26.03759765625,
    "memory_percent": 0.17547607421875,
    "disk_usage": 0.0,
    "tool_name": "mcp__context7__resolve-library-id",
    "execution_time": 1758970946.735126
  },
  {
    "timestamp": "2025-09-27T13:02:32.097787",
    "cpu_percent": 24.951171875,
    "memory_percent": 0.1758575439453125,
    "disk_usage": 0.0,
    "tool_name": "mcp__context7__get-library-docs",
    "execution_time": 1758970952.097816
  },
  {
    "timestamp": "2025-09-27T13:02:39.549934",
    "cpu_percent": 24.951171875,
    "memory_percent": 0.18367767333984375,
    "disk_usage": 0.0,
    "tool_name": "TodoWrite",
    "execution_time": 1758970959.550221
  },
  {
    "timestamp": "2025-09-27T13:03:29.025694",
    "cpu_percent": 20.977783203125,
    "memory_percent": 0.18596649169921875,
    "disk_usage": 0.0,
    "tool_name": "TodoWrite",
    "execution_time": 1758971009.0257149
  },
  {
    "timestamp": "2025-09-27T13:03:58.693867",
    "cpu_percent": 22.467041015625,
    "memory_percent": 0.1827239990234375,
    "disk_usage": 0.0,
    "tool_name": "Edit",
    "execution_time": 1758971038.693971
  },
  {
    "timestamp": "2025-09-27T13:04:26.611414",
    "cpu_percent": 20.7763671875,
    "memory_percent": 0.18157958984375,
    "disk_usage": 0.0,
    "tool_name": "Edit",
    "execution_time": 1758971066.6114419
  },
  {
    "timestamp": "2025-09-27T13:04:32.959473",
    "cpu_percent": 20.111083984375,
    "memory_percent": 0.1773834228515625,
    "disk_usage": 0.0,
    "tool_name": "TodoWrite",
    "execution_time": 1758971072.959498
  },
  {
    "timestamp": "2025-09-27T13:17:09.871088",
    "cpu_percent": 15.509033203125,
    "memory_percent": 0.18329620361328125,
    "disk_usage": 0.0,
    "tool_name": "TodoWrite",
    "execution_time": 1758971829.871125
  },
  {
    "timestamp": "2025-09-27T13:17:45.351709",
    "cpu_percent": 16.73583984375,
    "memory_percent": 0.17795562744140625,
    "disk_usage": 0.0,
    "tool_name": "mcp__context7__resolve-library-id",
    "execution_time": 1758971865.351768
  },
  {
    "timestamp": "2025-09-27T13:17:50.784963",
    "cpu_percent": 17.39501953125,
    "memory_percent": 0.18062591552734375,
    "disk_usage": 0.0,
    "tool_name": "mcp__context7__get-library-docs",
    "execution_time": 1758971870.784999
  },
  {
    "timestamp": "2025-09-27T13:17:57.509004",
    "cpu_percent": 22.003173828125,
    "memory_percent": 0.17833709716796875,
    "disk_usage": 0.0,
    "tool_name": "TodoWrite",
    "execution_time": 1758971877.509027
  },
  {
    "timestamp": "2025-09-27T13:18:06.553278",
    "cpu_percent": 26.141357421875,
    "memory_percent": 0.18978118896484375,
    "disk_usage": 0.0,
    "tool_name": "Read",
    "execution_time": 1758971886.553351
  },
  {
    "timestamp": "2025-09-27T13:18:21.474064",
    "cpu_percent": 27.490234375,
    "memory_percent": 0.186920166015625,
    "disk_usage": 0.0,
    "tool_name": "Edit",
    "execution_time": 1758971901.474096
  },
  {
    "timestamp": "2025-09-27T13:18:29.762588",
    "cpu_percent": 25.18310546875,
    "memory_percent": 0.18672943115234375,
    "disk_usage": 0.0,
    "tool_name": "Edit",
    "execution_time": 1758971909.762614
  },
  {
    "timestamp": "2025-09-27T13:18:46.216183",
    "cpu_percent": 23.05908203125,
    "memory_percent": 0.18329620361328125,
    "disk_usage": 0.0,
    "tool_name": "Edit",
    "execution_time": 1758971926.2162502
  },
  {
    "timestamp": "2025-09-27T13:18:51.351669",
    "cpu_percent": 22.210693359375,
    "memory_percent": 0.1850128173828125,
    "disk_usage": 0.0,
    "tool_name": "TodoWrite",
    "execution_time": 1758971931.351691
  },
  {
    "timestamp": "2025-09-27T13:19:02.738153",
    "cpu_percent": 20.6298828125,
    "memory_percent": 0.1819610595703125,
    "disk_usage": 0.0,
    "tool_name": "Edit",
    "execution_time": 1758971942.73826
  },
  {
    "timestamp": "2025-09-27T13:19:11.403523",
    "cpu_percent": 18.37158203125,
    "memory_percent": 0.1857757568359375,
    "disk_usage": 0.0,
    "tool_name": "Edit",
    "execution_time": 1758971951.4035468
  },
  {
    "timestamp": "2025-09-27T13:19:35.810009",
    "cpu_percent": 28.2470703125,
    "memory_percent": 0.18482208251953125,
    "disk_usage": 0.0,
    "tool_name": "Edit",
    "execution_time": 1758971975.8101828
  },
  {
    "timestamp": "2025-09-27T13:19:42.206701",
    "cpu_percent": 29.986572265625,
    "memory_percent": 0.1850128173828125,
    "disk_usage": 0.0,
    "tool_name": "TodoWrite",
    "execution_time": 1758971982.206727
  },
  {
    "timestamp": "2025-09-27T13:19:51.432369",
    "cpu_percent": 31.0546875,
    "memory_percent": 0.18634796142578125,
    "disk_usage": 0.0,
    "tool_name": "Edit",
    "execution_time": 1758971991.432427
  },
  {
    "timestamp": "2025-09-27T13:19:57.724966",
    "cpu_percent": 31.5673828125,
    "memory_percent": 0.194549560546875,
    "disk_usage": 0.0,
    "tool_name": "Edit",
    "execution_time": 1758971997.724997
  },
  {
    "timestamp": "2025-09-27T13:20:05.639444",
    "cpu_percent": 32.62939453125,
    "memory_percent": 0.1873016357421875,
    "disk_usage": 0.0,
    "tool_name": "Edit",
    "execution_time": 1758972005.639474
  },
  {
    "timestamp": "2025-09-27T13:20:13.168831",
    "cpu_percent": 35.015869140625,
    "memory_percent": 0.179290771484375,
    "disk_usage": 0.0,
    "tool_name": "TodoWrite",
    "execution_time": 1758972013.1688561
  },
  {
    "timestamp": "2025-09-27T13:20:18.206264",
    "cpu_percent": 35.211181640625,
    "memory_percent": 0.185394287109375,
    "disk_usage": 0.0,
    "tool_name": "Bash",
    "execution_time": 1758972018.2062879
  },
  {
    "timestamp": "2025-09-27T13:20:25.007056",
    "cpu_percent": 35.7177734375,
    "memory_percent": 0.1796722412109375,
    "disk_usage": 0.0,
    "tool_name": "Bash",
    "execution_time": 1758972025.007079
  },
  {
    "timestamp": "2025-09-27T13:20:28.896331",
    "cpu_percent": 35.7177734375,
    "memory_percent": 0.18024444580078125,
    "disk_usage": 0.0,
    "tool_name": "Bash",
    "execution_time": 1758972028.896353
  },
  {
    "timestamp": "2025-09-27T13:20:34.730580",
    "cpu_percent": 35.858154296875,
    "memory_percent": 0.17871856689453125,
    "disk_usage": 0.0,
    "tool_name": "Bash",
    "execution_time": 1758972034.730613
  },
  {
    "timestamp": "2025-09-27T13:20:38.678956",
    "cpu_percent": 41.9921875,
    "memory_percent": 0.1758575439453125,
    "disk_usage": 0.0,
    "tool_name": "Bash",
    "execution_time": 1758972038.6789918
  },
  {
    "timestamp": "2025-09-27T13:34:33.635650",
    "cpu_percent": 33.697509765625,
    "memory_percent": 0.18310546875,
    "disk_usage": 0.0,
    "tool_name": "Bash",
    "execution_time": 1758972873.6356852
  },
  {
    "timestamp": "2025-09-27T13:34:38.694216",
    "cpu_percent": 32.99560546875,
    "memory_percent": 0.1850128173828125,
    "disk_usage": 0.0,
    "tool_name": "Bash",
    "execution_time": 1758972878.694242
  },
  {
    "timestamp": "2025-09-27T13:34:42.124621",
    "cpu_percent": 33.355712890625,
    "memory_percent": 0.182342529296875,
    "disk_usage": 0.0,
    "tool_name": "Bash",
    "execution_time": 1758972882.1246898
  },
  {
    "timestamp": "2025-09-27T13:34:48.149253",
    "cpu_percent": 32.684326171875,
    "memory_percent": 0.18291473388671875,
    "disk_usage": 0.0,
    "tool_name": "TodoWrite",
    "execution_time": 1758972888.149277
  },
  {
    "timestamp": "2025-09-27T13:34:53.197508",
    "cpu_percent": 31.06689453125,
    "memory_percent": 0.177764892578125,
    "disk_usage": 0.0,
    "tool_name": "Bash",
    "execution_time": 1758972893.1975338
  },
  {
    "timestamp": "2025-09-27T13:35:05.359334",
    "cpu_percent": 29.1259765625,
    "memory_percent": 0.18978118896484375,
    "disk_usage": 0.0,
    "tool_name": "Edit",
    "execution_time": 1758972905.35937
  },
  {
    "timestamp": "2025-09-27T13:35:14.551119",
    "cpu_percent": 40.496826171875,
    "memory_percent": 0.19245147705078125,
    "disk_usage": 0.0,
    "tool_name": "Edit",
    "execution_time": 1758972914.551144
  },
  {
    "timestamp": "2025-09-27T13:35:20.216456",
    "cpu_percent": 40.252685546875,
    "memory_percent": 0.179290771484375,
    "disk_usage": 0.0,
    "tool_name": "Bash",
    "execution_time": 1758972920.216481
  },
  {
    "timestamp": "2025-09-27T13:35:29.383598",
    "cpu_percent": 35.980224609375,
    "memory_percent": 0.1773834228515625,
    "disk_usage": 0.0,
    "tool_name": "TodoWrite",
    "execution_time": 1758972929.383635
  },
  {
    "timestamp": "2025-09-27T14:10:18.147378",
    "cpu_percent": 26.85546875,
    "memory_percent": 0.18405914306640625,
    "disk_usage": 0.0,
    "tool_name": "TodoWrite",
    "execution_time": 1758975018.1474051
  },
  {
    "timestamp": "2025-09-27T14:10:50.617362",
    "cpu_percent": 31.18896484375,
    "memory_percent": 0.17642974853515625,
    "disk_usage": 0.0,
    "tool_name": "mcp__context7__resolve-library-id",
    "execution_time": 1758975050.617399
  },
  {
    "timestamp": "2025-09-27T14:10:56.387753",
    "cpu_percent": 32.6904296875,
    "memory_percent": 0.174713134765625,
    "disk_usage": 0.0,
    "tool_name": "mcp__context7__get-library-docs",
    "execution_time": 1758975056.387788
  },
  {
    "timestamp": "2025-09-27T14:11:33.558617",
    "cpu_percent": 29.443359375,
    "memory_percent": 0.19092559814453125,
    "disk_usage": 0.0,
    "tool_name": "Edit",
    "execution_time": 1758975093.558646
  },
  {
    "timestamp": "2025-09-27T14:11:47.506308",
    "cpu_percent": 90.36865234375,
    "memory_percent": 0.189208984375,
    "disk_usage": 0.0,
    "tool_name": "Edit",
    "execution_time": 1758975107.5063412
  },
  {
    "timestamp": "2025-09-27T14:11:53.482487",
    "cpu_percent": 83.99658203125,
    "memory_percent": 0.177764892578125,
    "disk_usage": 0.0,
    "tool_name": "TodoWrite",
    "execution_time": 1758975113.4825118
  },
  {
    "timestamp": "2025-09-27T14:12:05.682507",
    "cpu_percent": 81.524658203125,
    "memory_percent": 0.18978118896484375,
    "disk_usage": 0.0,
    "tool_name": "Edit",
    "execution_time": 1758975125.683248
  },
  {
    "timestamp": "2025-09-27T14:12:19.655325",
    "cpu_percent": 66.143798828125,
    "memory_percent": 0.19245147705078125,
    "disk_usage": 0.0,
    "tool_name": "Edit",
    "execution_time": 1758975139.655353
  },
  {
    "timestamp": "2025-09-27T14:12:26.920679",
    "cpu_percent": 63.848876953125,
    "memory_percent": 0.1811981201171875,
    "disk_usage": 0.0,
    "tool_name": "Bash",
    "execution_time": 1758975146.920705
  },
  {
    "timestamp": "2025-09-27T14:12:43.381155",
    "cpu_percent": 53.02734375,
    "memory_percent": 0.18672943115234375,
    "disk_usage": 0.0,
    "tool_name": "Bash",
    "execution_time": 1758975163.3811898
  },
  {
    "timestamp": "2025-09-27T14:12:50.924160",
    "cpu_percent": 48.779296875,
    "memory_percent": 0.17681121826171875,
    "disk_usage": 0.0,
    "tool_name": "Bash",
    "execution_time": 1758975170.924182
  },
  {
    "timestamp": "2025-09-27T14:12:54.869037",
    "cpu_percent": 46.875,
    "memory_percent": 0.17948150634765625,
    "disk_usage": 0.0,
    "tool_name": "Bash",
    "execution_time": 1758975174.8690681
  },
  {
    "timestamp": "2025-09-27T14:13:00.322090",
    "cpu_percent": 44.122314453125,
    "memory_percent": 0.1800537109375,
    "disk_usage": 0.0,
    "tool_name": "TodoWrite",
    "execution_time": 1758975180.3221161
  },
  {
    "timestamp": "2025-09-27T14:13:06.188739",
    "cpu_percent": 41.58935546875,
    "memory_percent": 0.18310546875,
    "disk_usage": 0.0,
    "tool_name": "Bash",
    "execution_time": 1758975186.188763
  },
  {
    "timestamp": "2025-09-27T14:13:26.292616",
    "cpu_percent": 34.515380859375,
    "memory_percent": 0.17910003662109375,
    "disk_usage": 0.0,
    "tool_name": "TodoWrite",
    "execution_time": 1758975206.2926688
  },
  {
    "timestamp": "2025-09-27T14:14:25.422964",
    "cpu_percent": 29.083251953125,
    "memory_percent": 0.18444061279296875,
    "disk_usage": 0.0,
    "tool_name": "TodoWrite",
    "execution_time": 1758975265.422992
  },
  {
    "timestamp": "2025-09-27T14:15:19.368260",
    "cpu_percent": 28.729248046875,
    "memory_percent": 0.19397735595703125,
    "disk_usage": 0.0,
    "tool_name": "Edit",
    "execution_time": 1758975319.3682969
  },
  {
    "timestamp": "2025-09-27T14:15:26.922402",
    "cpu_percent": 28.43017578125,
    "memory_percent": 0.19397735595703125,
    "disk_usage": 0.0,
    "tool_name": "Edit",
    "execution_time": 1758975326.922472
  },
  {
    "timestamp": "2025-09-27T14:15:34.367946",
    "cpu_percent": 28.973388671875,
    "memory_percent": 0.18634796142578125,
    "disk_usage": 0.0,
    "tool_name": "Edit",
    "execution_time": 1758975334.3679738
  },
  {
    "timestamp": "2025-09-27T14:15:40.410478",
    "cpu_percent": 28.64990234375,
    "memory_percent": 0.17871856689453125,
    "disk_usage": 0.0,
    "tool_name": "TodoWrite",
    "execution_time": 1758975340.4105039
  },
  {
    "timestamp": "2025-09-27T14:15:49.125472",
    "cpu_percent": 30.0048828125,
    "memory_percent": 0.189208984375,
    "disk_usage": 0.0,
    "tool_name": "Edit",
    "execution_time": 1758975349.125557
  },
  {
    "timestamp": "2025-09-27T14:15:58.777347",
    "cpu_percent": 28.60107421875,
    "memory_percent": 0.1873016357421875,
    "disk_usage": 0.0,
    "tool_name": "Edit",
    "execution_time": 1758975358.7773812
  },
  {
    "timestamp": "2025-09-27T14:16:04.328232",
    "cpu_percent": 30.04150390625,
    "memory_percent": 0.183868408203125,
    "disk_usage": 0.0,
    "tool_name": "Bash",
    "execution_time": 1758975364.328257
  },
  {
    "timestamp": "2025-09-27T14:16:23.465962",
    "cpu_percent": 24.298095703125,
    "memory_percent": 0.17948150634765625,
    "disk_usage": 0.0,
    "tool_name": "Bash",
    "execution_time": 1758975383.4659991
  },
  {
    "timestamp": "2025-09-27T14:16:30.608129",
    "cpu_percent": 20.556640625,
    "memory_percent": 0.183868408203125,
    "disk_usage": 0.0,
    "tool_name": "Bash",
    "execution_time": 1758975390.608156
  },
  {
    "timestamp": "2025-09-27T14:17:17.440435",
    "cpu_percent": 19.9462890625,
    "memory_percent": 0.177001953125,
    "disk_usage": 0.0,
    "tool_name": "TodoWrite",
    "execution_time": 1758975437.440473
  },
  {
    "timestamp": "2025-09-27T14:17:21.530704",
    "cpu_percent": 19.34814453125,
    "memory_percent": 0.18329620361328125,
    "disk_usage": 0.0,
    "tool_name": "Bash",
    "execution_time": 1758975441.530733
  },
  {
    "timestamp": "2025-09-27T14:19:42.709824",
    "cpu_percent": 15.95458984375,
    "memory_percent": 0.17833709716796875,
    "disk_usage": 0.0,
    "tool_name": "Bash",
    "execution_time": 1758975582.709853
  },
  {
    "timestamp": "2025-09-27T14:19:47.678977",
    "cpu_percent": 18.6767578125,
    "memory_percent": 0.17681121826171875,
    "disk_usage": 0.0,
    "tool_name": "Bash",
    "execution_time": 1758975587.6790242
  },
  {
    "timestamp": "2025-09-27T14:20:04.106523",
    "cpu_percent": 17.37060546875,
    "memory_percent": 0.17032623291015625,
    "disk_usage": 0.0,
    "tool_name": "TodoWrite",
    "execution_time": 1758975604.1065469
  },
  {
    "timestamp": "2025-09-27T14:26:04.927557",
    "cpu_percent": 19.354248046875,
    "memory_percent": 0.17948150634765625,
    "disk_usage": 0.0,
    "tool_name": "TodoWrite",
    "execution_time": 1758975964.927595
  },
  {
    "timestamp": "2025-09-27T14:26:34.748655",
    "cpu_percent": 22.8759765625,
    "memory_percent": 0.17833709716796875,
    "disk_usage": 0.0,
    "tool_name": "mcp__context7__resolve-library-id",
    "execution_time": 1758975994.74869
  },
  {
    "timestamp": "2025-09-27T14:26:39.454677",
    "cpu_percent": 32.049560546875,
    "memory_percent": 0.18138885498046875,
    "disk_usage": 0.0,
    "tool_name": "mcp__context7__get-library-docs",
    "execution_time": 1758975999.454738
  },
  {
    "timestamp": "2025-09-27T14:26:46.006571",
    "cpu_percent": 31.48193359375,
    "memory_percent": 0.18711090087890625,
    "disk_usage": 0.0,
    "tool_name": "TodoWrite",
    "execution_time": 1758976006.006604
  },
  {
    "timestamp": "2025-09-27T14:26:50.302057",
    "cpu_percent": 68.994140625,
    "memory_percent": 0.1781463623046875,
    "disk_usage": 0.0,
    "tool_name": "Read",
    "execution_time": 1758976010.302082
  },
  {
    "timestamp": "2025-09-27T14:26:56.702698",
    "cpu_percent": 61.3037109375,
    "memory_percent": 0.177764892578125,
    "disk_usage": 0.0,
    "tool_name": "Bash",
    "execution_time": 1758976016.702723
  },
  {
    "timestamp": "2025-09-27T14:27:00.195972",
    "cpu_percent": 61.3037109375,
    "memory_percent": 0.17852783203125,
    "disk_usage": 0.0,
    "tool_name": "Bash",
    "execution_time": 1758976020.195998
  },
  {
    "timestamp": "2025-09-27T14:27:06.771990",
    "cpu_percent": 56.634521484375,
    "memory_percent": 0.1781463623046875,
    "disk_usage": 0.0,
    "tool_name": "Edit",
    "execution_time": 1758976026.772015
  },
  {
    "timestamp": "2025-09-27T14:27:10.281601",
    "cpu_percent": 56.634521484375,
    "memory_percent": 0.17852783203125,
    "disk_usage": 0.0,
    "tool_name": "Read",
    "execution_time": 1758976030.281628
  },
  {
    "timestamp": "2025-09-27T14:27:21.845088",
    "cpu_percent": 61.309814453125,
    "memory_percent": 0.17852783203125,
    "disk_usage": 0.0,
    "tool_name": "Edit",
    "execution_time": 1758976041.8452532
  },
  {
    "timestamp": "2025-09-27T14:27:33.641710",
    "cpu_percent": 54.718017578125,
    "memory_percent": 0.185394287109375,
    "disk_usage": 0.0,
    "tool_name": "Edit",
    "execution_time": 1758976053.641773
  },
  {
    "timestamp": "2025-09-27T14:27:44.186233",
    "cpu_percent": 49.224853515625,
    "memory_percent": 0.18253326416015625,
    "disk_usage": 0.0,
    "tool_name": "Edit",
    "execution_time": 1758976064.186259
  },
  {
    "timestamp": "2025-09-27T14:27:59.732833",
    "cpu_percent": 42.93212890625,
    "memory_percent": 0.17833709716796875,
    "disk_usage": 0.0,
    "tool_name": "Edit",
    "execution_time": 1758976079.732908
  },
  {
    "timestamp": "2025-09-27T14:28:14.514971",
    "cpu_percent": 35.260009765625,
    "memory_percent": 0.17223358154296875,
    "disk_usage": 0.0,
    "tool_name": "Edit",
    "execution_time": 1758976094.515002
  },
  {
    "timestamp": "2025-09-27T14:28:22.222267",
    "cpu_percent": 31.756591796875,
    "memory_percent": 0.1850128173828125,
    "disk_usage": 0.0,
    "tool_name": "Read",
    "execution_time": 1758976102.222293
  },
  {
    "timestamp": "2025-09-27T14:28:32.066934",
    "cpu_percent": 38.56201171875,
    "memory_percent": 0.180816650390625,
    "disk_usage": 0.0,
    "tool_name": "Edit",
    "execution_time": 1758976112.0669599
  },
  {
    "timestamp": "2025-09-27T14:34:46.040621",
    "cpu_percent": 20.184326171875,
    "memory_percent": 0.18100738525390625,
    "disk_usage": 0.0,
    "tool_name": "Bash",
    "execution_time": 1758976486.0406442
  },
  {
    "timestamp": "2025-09-27T14:34:51.485999",
    "cpu_percent": 21.56982421875,
    "memory_percent": 0.1842498779296875,
    "disk_usage": 0.0,
    "tool_name": "Edit",
    "execution_time": 1758976491.486026
  },
  {
    "timestamp": "2025-09-27T14:35:03.308807",
    "cpu_percent": 27.01416015625,
    "memory_percent": 0.183868408203125,
    "disk_usage": 0.0,
    "tool_name": "Bash",
    "execution_time": 1758976503.308832
  },
  {
    "timestamp": "2025-09-27T14:35:08.483130",
    "cpu_percent": 26.849365234375,
    "memory_percent": 0.17852783203125,
    "disk_usage": 0.0,
    "tool_name": "Bash",
    "execution_time": 1758976508.4831529
  },
  {
    "timestamp": "2025-09-27T14:35:12.753806",
    "cpu_percent": 26.69677734375,
    "memory_percent": 0.17795562744140625,
    "disk_usage": 0.0,
    "tool_name": "Bash",
    "execution_time": 1758976512.7538319
  },
  {
    "timestamp": "2025-09-27T14:35:52.481720",
    "cpu_percent": 26.611328125,
    "memory_percent": 0.1857757568359375,
    "disk_usage": 0.0,
    "tool_name": "Write",
    "execution_time": 1758976552.481749
  },
  {
    "timestamp": "2025-09-27T14:36:12.767660",
    "cpu_percent": 42.633056640625,
    "memory_percent": 0.18310546875,
    "disk_usage": 0.0,
    "tool_name": "Bash",
    "execution_time": 1758976572.7676852
  },
  {
    "timestamp": "2025-09-27T14:36:17.275074",
    "cpu_percent": 42.633056640625,
    "memory_percent": 0.1796722412109375,
    "disk_usage": 0.0,
    "tool_name": "Read",
    "execution_time": 1758976577.2750971
  },
  {
    "timestamp": "2025-09-27T14:36:22.972995",
    "cpu_percent": 37.9150390625,
    "memory_percent": 0.19016265869140625,
    "disk_usage": 0.0,
    "tool_name": "Edit",
    "execution_time": 1758976582.9731112
  }
]